Workbook
Name Orders: #REF!
Name People: #REF!
Name Returns: #REF!

Sheet Orders
A1: Row ID | B1: Order ID | C1: Order Date | D1: Ship Date | E1: Ship Mode | F1: Customer ID | G1: Customer Name | H1: Segment | I1: Country/Region | J1: City | K1: State/Province | L1: Postal Code | M1: Region | N1: Product ID | O1: Category | P1: Sub-Category | Q1: Product Name | R1: Sales | S1: Quantity | T1: Discount | U1: Profit
A2: 1 | B2: US-2023-103800 | C2: 44929 | D2: 44933 | E2: Standard Class | F2: DP-13000 | G2: Darren Powers | H2: Consumer | I2: United States | J2: Houston | K2: Texas | L2: 77095 | M2: Central | N2: OFF-PA-10000174 | O2: Office Supplies | P2: Paper | Q2: Message Book, Wirebound, Four 5 1/2" X 4" Forms/Pg., 200 Dupl. Sets/Book | R2: 16.448 | S2: 2 | T2: 0.2 | U2: 5.5512
A3: 2 | B3: US-2023-112326 | C3: 44930 | D3: 44934 | E3: Standard Class | F3: PO-19195 | G3: Phillina Ober | H3: Home Office | I3: United States | J3: Naperville | K3: Illinois | L3: 60540 | M3: Central | N3: OFF-BI-10004094 | O3: Office Supplies | P3: Binders | Q3: GBC Standard Plastic Binding Systems Combs | R3: 3.54 | S3: 2 | T3: 0.8 | U3: -5.487
A4: 3 | B4: US-2023-112326 | C4: 44930 | D4: 44934 | E4: Standard Class | F4: PO-19195 | G4: Phillina Ober | H4: Home Office | I4: United States | J4: Naperville | K4: Illinois | L4: 60540 | M4: Central | N4: OFF-LA-10003223 | O4: Office Supplies | P4: Labels | Q4: Avery 508 | R4: 11.784 | S4: 3 | T4: 0.2 | U4: 4.2717
A5: 4 | B5: US-2023-112326 | C5: 44930 | D5: 44934 | E5: Standard Class | F5: PO-19195 | G5: Phillina Ober | H5: Home Office | I5: United States | J5: Naperville | K5: Illinois | L5: 60540 | M5: Central | N5: OFF-ST-10002743 | O5: Office Supplies | P5: Storage | Q5: SAFCO Boltless Steel Shelving | R5: 272.736 | S5: 3 | T5: 0.2 | U5: -64.7748
A6: 5 | B6: US-2023-141817 | C6: 44931 | D6: 44938 | E6: Standard Class | F6: MB-18085 | G6: Mick Brown | H6: Consumer | I6: United States | J6: Philadelphia | K6: Pennsylvania | L6: 19143 | M6: East | N6: OFF-AR-10003478 | O6: Office Supplies | P6: Art | Q6: Avery Hi-Liter EverBold Pen Style Fluorescent Highlighters, 4/Pack | R6: 19.536 | S6: 3 | T6: 0.2 | U6: 4.884
A7: 6 | B7: US-2023-167199 | C7: 44932 | D7: 44936 | E7: Standard Class | F7: ME-17320 | G7: Maria Etezadi | H7: Home Office | I7: United States | J7: Henderson | K7: Kentucky | L7: 42420 | M7: South | N7: FUR-CH-10004063 | O7: Furniture | P7: Chairs | Q7: Global Deluxe High-Back Manager's Chair | R7: 2573.82 | S7: 9 | T7: 0 | U7: 746.4078
A8: 7 | B8: US-2023-167199 | C8: 44932 | D8: 44936 | E8: Standard Class | F8: ME-17320 | G8: Maria Etezadi | H8: Home Office | I8: United States | J8: Henderson | K8: Kentucky | L8: 42420 | M8: South | N8: OFF-AR-10001662 | O8: Office Supplies | P8: Art | Q8: Rogers Handheld Barrel Pencil Sharpener | R8: 5.48 | S8: 2 | T8: 0 | U8: 1.4796
A9: 8 | B9: US-2023-106054 | C9: 44932 | D9: 44933 | E9: First Class | F9: JO-15145 | G9: Jack O'Briant | H9: Corporate | I9: United States | J9: Athens | K9: Georgia | L9: 30605 | M9: South | N9: OFF-AR-10002399 | O9: Office Supplies | P9: Art | Q9: Dixon Prang Watercolor Pencils, 10-Color Set with Brush | R9: 12.78 | S9: 3 | T9: 0 | U9: 5.2398
A10: 9 | B10: US-2023-167199 | C10: 44932 | D10: 44936 | E10: Standard Class | F10: ME-17320 | G10: Maria Etezadi | H10: Home Office | I10: United States | J10: Henderson | K10: Kentucky | L10: 42420 | M10: South | N10: OFF-BI-10004632 | O10: Office Supplies | P10: Binders | Q10: Ibico Hi-Tech Manual Binding System | R10: 609.98 | S10: 2 | T10: 0 | U10: 274.491
A11: 10 | B11: US-2023-167199 | C11: 44932 | D11: 44936 | E11: Standard Class | F11: ME-17320 | G11: Maria Etezadi | H11: Home Office | I11: United States | J11: Henderson | K11: Kentucky | L11: 42420 | M11: South | N11: OFF-FA-10001883 | O11: Office Supplies | P11: Fasteners | Q11: Alliance Super-Size Bands, Assorted Sizes | R11: 31.12 | S11: 4 | T11: 0 | U11: 0.3112
A12: 11 | B12: US-2023-167199 | C12: 44932 | D12: 44936 | E12: Standard Class | F12: ME-17320 | G12: Maria Etezadi | H12: Home Office | I12: United States | J12: Henderson | K12: Kentucky | L12: 42420 | M12: South | N12: OFF-PA-10000955 | O12: Office Supplies | P12: Paper | Q12: Southworth 25% Cotton Granite Paper & Envelopes | R12: 6.54 | S12: 1 | T12: 0 | U12: 3.0084
A13: 12 | B13: US-2023-130813 | C13: 44932 | D13: 44934 | E13: Second Class | F13: LS-17230 | G13: Lycoris Saunders | H13: Consumer | I13: United States | J13: Los Angeles | K13: California | L13: 90049 | M13: West | N13: OFF-PA-10002005 | O13: Office Supplies | P13: Paper | Q13: Xerox 225 | R13: 19.44 | S13: 3 | T13: 0 | U13: 9.3312
... A62: 61 | B62: US-2023-110422 | C62: 44947 | D62: 44949 | E62: Second Class | F62: TB-21400 | G62: Tom Boeckenhauer | H62: Consumer | I62: United States | J62: Miami | K62: Florida | L62: 33180 | M62: South | N62: FUR-FU-10001889 | O62: Furniture | P62: Furnishings | Q62: Ultra Door Pull Handle | R62: 25.248 | S62: 3 | T62: 0.2 | U62: 4.1028
A63: 62 | B63: CA-2023-115238 | C63: 44947 | D63: 44950 | E63: Standard Class | F63: JW-15220 | G63: Jane Waco | H63: Corporate | I63: Canada | J63: Toronto | K63: Ontario | L63: M7A | M63: East | N63: FUR-FU-10001025 | O63: Furniture | P63: Furnishings | Q63: Eldon Imàge Series Desk Accessories, Clear | R63: 24.3 | S63: 5 | T63: 0 | U63: 10.45
A64: 63 | B64: CA-2023-115238 | C64: 44947 | D64: 44950 | E64: Standard Class | F64: JW-15220 | G64: Jane Waco | H64: Corporate | I64: Canada | J64: Toronto | K64: Ontario | L64: M7A | M64: East | N64: FUR-FU-10002445 | O64: Furniture | P64: Furnishings | Q64: DAX Two-Tone Rosewood/Black Document Frame, Desktop, 5 x 7 | R64: 9.48 | S64: 1 | T64: 0 | U64: 3.79
A65: 64 | B65: CA-2023-115238 | C65: 44947 | D65: 44950 | E65: Standard Class | F65: JW-15220 | G65: Jane Waco | H65: Corporate | I65: Canada | J65: Toronto | K65: Ontario | L65: M7A | M65: East | N65: FUR-FU-10002960 | O65: Furniture | P65: Furnishings | Q65: Eldon 200 Class Desk Accessories, Burgundy | R65: 31.4 | S65: 5 | T65: 0 | U65: 13.19
A66: 65 | B66: CA-2023-115238 | C66: 44947 | D66: 44950 | E66: Standard Class | F66: JW-15220 | G66: Jane Waco | H66: Corporate | I66: Canada | J66: Toronto | K66: Ontario | L66: M7A | M66: East | N66: OFF-PA-10002689 | O66: Office Supplies | P66: Paper | Q66: Weyerhaeuser First Choice Laser/Copy Paper (20Lb. and 88 Bright) | R66: 6.48 | S66: 1 | T66: 0 | U66: 3.11
A67: 66 | B67: CA-2023-115238 | C67: 44947 | D67: 44950 | E67: Standard Class | F67: JW-15220 | G67: Jane Waco | H67: Corporate | I67: Canada | J67: Toronto | K67: Ontario | L67: M7A | M67: East | N67: TEC-PH-10001300 | O67: Technology | P67: Phones | Q67: iKross Bluetooth Portable Keyboard + Cell Phone Stand Holder + Brush for Apple iPhone 5S 5C 5, 4S 4 | R67: 209.5 | S67: 10 | T67: 0 | U67: 58.66
A68: 67 | B68: US-2023-146997 | C68: 44949 | D68: 44953 | E68: Standard Class | F68: SG-20605 | G68: Speros Goranitis | H68: Consumer | I68: United States | J68: Lafayette | K68: Indiana | L68: 47905 | M68: Central | N68: OFF-FA-10003467 | O68: Office Supplies | P68: Fasteners | Q68: Alliance Big Bands Rubber Bands, 12/Pack | R68: 5.94 | S68: 3 | T68: 0 | U68: 0
A69: 68 | B69: US-2023-102645 | C69: 44949 | D69: 44954 | E69: Standard Class | F69: IM-15055 | G69: Ionia McGrath | H69: Consumer | I69: United States | J69: Las Vegas | K69: Nevada | L69: 89115 | M69: West | N69: OFF-PA-10001804 | O69: Office Supplies | P69: Paper | Q69: Xerox 195 | R69: 40.08 | S69: 6 | T69: 0 | U69: 19.2384
A70: 69 | B70: US-2023-167997 | C70: 44952 | D70: 44955 | E70: First Class | F70: CA-11965 | G70: Carol Adams | H70: Corporate | I70: United States | J70: Rapid City | K70: South Dakota | L70: 57701 | M70: Central | N70: FUR-BO-10004409 | O70: Furniture | P70: Bookcases | Q70: Safco Value Mate Series Steel Bookcases, Baked Enamel Finish on Steel, Gray | R70: 141.96 | S70: 2 | T70: 0 | U70: 39.7488
A71: 70 | B71: US-2023-155502 | C71: 44952 | D71: 44957 | E71: Standard Class | F71: SD-20485 | G71: Shirley Daniels | H71: Home Office | I71: United States | J71: Alexandria | K71: Virginia | L71: 22304 | M71: South | N71: FUR-FU-10001847 | O71: Furniture | P71: Furnishings | Q71: Eldon Image Series Black Desk Accessories | R71: 12.42 | S71: 3 | T71: 0 | U71: 4.4712
A72: 71 | B72: US-2023-155502 | C72: 44952 | D72: 44957 | E72: Standard Class | F72: SD-20485 | G72: Shirley Daniels | H72: Home Office | I72: United States | J72: Alexandria | K72: Virginia | L72: 22304 | M72: South | N72: FUR-FU-10004587 | O72: Furniture | P72: Furnishings | Q72: GE General Use Halogen Bulbs, 100 Watts, 1 Bulb per Pack | R72: 62.82 | S72: 3 | T72: 0 | U72: 30.7818
A73: 72 | B73: US-2023-167997 | C73: 44952 | D73: 44955 | E73: First Class | F73: CA-11965 | G73: Carol Adams | H73: Corporate | I73: United States | J73: Rapid City | K73: South Dakota | L73: 57701 | M73: Central | N73: OFF-BI-10001758 | O73: Office Supplies | P73: Binders | Q73: Wilson Jones 14 Line Acrylic Coated Pressboard Data Binders | R73: 10.68 | S73: 2 | T73: 0 | U73: 5.0196
A74: 73 | B74: US-2023-155502 | C74: 44952 | D74: 44957 | E74: Standard Class | F74: SD-20485 | G74: Shirley Daniels | H74: Home Office | I74: United States | J74: Alexandria | K74: Virginia | L74: 22304 | M74: South | N74: OFF-PA-10000380 | O74: Office Supplies | P74: Paper | Q74: REDIFORM Incoming/Outgoing Call Register, 11" X 8 1/2", 100 Messages | R74: 16.68 | S74: 2 | T74: 0 | U74: 8.34
A75: 74 | B75: US-2023-155502 | C75: 44952 | D75: 44957 | E75: Standard Class | F75: SD-20485 | G75: Shirley Daniels | H75: Home Office | I75: United States | J75: Alexandria | K75: Virginia | L75: 22304 | M75: South | N75: OFF-PA-10003072 | O75: Office Supplies | P75: Paper | Q75: Eureka Recycled Copy Paper 8 1/2" x 11", Ream | R75: 19.44 | S75: 3 | T75: 0 | U75: 9.3312
A76: 75 | B76: US-2023-155502 | C76: 44952 | D76: 44957 | E76: Standard Class | F76: SD-20485 | G76: Shirley Daniels | H76: Home Office | I76: United States | J76: Alexandria | K76: Virginia | L76: 22304 | M76: South | N76: OFF-ST-10004337 | O76: Office Supplies | P76: Storage | Q76: SAFCO Commercial Wire Shelving, 72h | R76: 489.92 | S76: 8 | T76: 0 | U76: 0
A77: 76 | B77: US-2023-155502 | C77: 44952 | D77: 44957 | E77: Standard Class | F77: SD-20485 | G77: Shirley Daniels | H77: Home Office | I77: United States | J77: Alexandria | K77: Virginia | L77: 22304 | M77: South | N77: TEC-PH-10002103 | O77: Technology | P77: Phones | Q77: Jabra SPEAK 410 | R77: 187.98 | S77: 2 | T77: 0 | U77: 52.6344
A78: 77 | B78: US-2023-155502 | C78: 44952 | D78: 44957 | E78: Standard Class | F78: SD-20485 | G78: Shirley Daniels | H78: Home Office | I78: United States | J78: Alexandria | K78: Virginia | L78: 22304 | M78: South | N78: TEC-PH-10004833 | O78: Technology | P78: Phones | Q78: Macally Suction Cup Mount | R78: 155.35 | S78: 13 | T78: 0 | U78: 0
A79: 78 | B79: US-2023-117163 | C79: 44953 | D79: 44959 | E79: Standard Class | F79: EJ-13720 | G79: Ed Jacobs | H79: Consumer | I79: United States | J79: San Diego | K79: California | L79: 92037 | M79: West | N79: FUR-TA-10003469 | O79: Furniture | P79: Tables | Q79: Balt Split Level Computer Training Table | R79: 333 | S79: 3 | T79: 0.2 | U79: -16.65
... A180: 179 | B180: US-2023-114790 | C180: 44996 | D180: 44998 | E180: Second Class | F180: FM-14215 | G180: Filia McAdams | H180: Corporate | I180: United States | J180: Richmond | K180: Kentucky | L180: 40475 | M180: South | N180: TEC-PH-10000984 | O180: Technology | P180: Phones | Q180: Panasonic KX-TG9471B | R180: 587.97 | S180: 3 | T180: 0 | U180: 164.6316
A181: 180 | B181: CA-2023-139675 | C181: 44998 | D181: 45003 | E181: Second Class | F181: NF-18595 | G181: Nicole Fjeld | H181: Home Office | I181: Canada | J181: Calgary | K181: Alberta | L181: T2C | M181: West | N181: FUR-CH-10004063 | O181: Furniture | P181: Chairs | Q181: Global Deluxe High-Back Manager's Chair | R181: 915.14 | S181: 4 | T181: 0.2 | U181: 102.95
A182: 181 | B182: CA-2023-139675 | C182: 44998 | D182: 45003 | E182: Second Class | F182: NF-18595 | G182: Nicole Fjeld | H182: Home Office | I182: Canada | J182: Calgary | K182: Alberta | L182: T2C | M182: West | N182: FUR-FU-10001979 | O182: Furniture | P182: Furnishings | Q182: Dana Halogen Swing-Arm Architect Lamp | R182: 327.76 | S182: 8 | T182: 0 | U182: 91.77
A183: 182 | B183: US-2023-125521 | C183: 44999 | D183: 45004 | E183: Standard Class | F183: CK-12325 | G183: Christine Kargatis | H183: Home Office | I183: United States | J183: Chesapeake | K183: Virginia | L183: 23320 | M183: South | N183: FUR-CH-10003379 | O183: Furniture | P183: Chairs | Q183: Global Commerce Series High-Back Swivel/Tilt Chairs | R183: 1139.92 | S183: 4 | T183: 0 | U183: 284.98
A184: 183 | B184: US-2023-157623 | C184: 44999 | D184: 45003 | E184: Standard Class | F184: DK-13225 | G184: Dean Katz | H184: Corporate | I184: United States | J184: Huntington Beach | K184: California | L184: 92646 | M184: West | N184: OFF-AR-10003723 | O184: Office Supplies | P184: Art | Q184: Avery Hi-Liter Fluorescent Desk Style Markers | R184: 3.38 | S184: 1 | T184: 0 | U184: 1.2506
A185: 184 | B185: US-2023-114510 | C185: 44999 | D185: 45004 | E185: Standard Class | F185: JF-15295 | G185: Jason Fortune- | H185: Consumer | I185: United States | J185: Logan | K185: Utah | L185: 84321 | M185: West | N185: OFF-BI-10001617 | O185: Office Supplies | P185: Binders | Q185: GBC Wire Binding Combs | R185: 33.088 | S185: 4 | T185: 0.2 | U185: 11.1672
A186: 185 | B186: US-2023-114510 | C186: 44999 | D186: 45004 | E186: Standard Class | F186: JF-15295 | G186: Jason Fortune- | H186: Consumer | I186: United States | J186: Logan | K186: Utah | L186: 84321 | M186: West | N186: OFF-BI-10003007 | O186: Office Supplies | P186: Binders | Q186: Premium Transparent Presentation Covers, No Pattern/Clear, 8 1/2" x 11" | R186: 62.048 | S186: 2 | T186: 0.2 | U186: 20.1656
A187: 186 | B187: US-2023-100293 | C187: 44999 | D187: 45003 | E187: Standard Class | F187: NF-18475 | G187: Neil Französisch | H187: Home Office | I187: United States | J187: Jacksonville | K187: Florida | L187: 32216 | M187: South | N187: OFF-PA-10000176 | O187: Office Supplies | P187: Paper | Q187: Xerox 1887 | R187: 91.056 | S187: 6 | T187: 0.2 | U187: 31.8696
A188: 187 | B188: US-2023-157623 | C188: 44999 | D188: 45003 | E188: Standard Class | F188: DK-13225 | G188: Dean Katz | H188: Corporate | I188: United States | J188: Huntington Beach | K188: California | L188: 92646 | M188: West | N188: OFF-PA-10001204 | O188: Office Supplies | P188: Paper | Q188: Xerox 1972 | R188: 10.56 | S188: 2 | T188: 0 | U188: 4.752
A189: 188 | B189: US-2023-152618 | C189: 44999 | D189: 45002 | E189: First Class | F189: RB-19465 | G189: Rick Bensley | H189: Home Office | I189: United States | J189: Chicago | K189: Illinois | L189: 60653 | M189: Central | N189: OFF-PA-10001215 | O189: Office Supplies | P189: Paper | Q189: Xerox 1963 | R189: 8.448 | S189: 2 | T189: 0.2 | U189: 2.64
A190: 189 | B190: US-2023-114510 | C190: 44999 | D190: 45004 | E190: Standard Class | F190: JF-15295 | G190: Jason Fortune- | H190: Consumer | I190: United States | J190: Logan | K190: Utah | L190: 84321 | M190: West | N190: OFF-ST-10000736 | O190: Office Supplies | P190: Storage | Q190: Carina Double Wide Media Storage Towers in Natural & Black | R190: 80.98 | S190: 1 | T190: 0 | U190: 3.2392
A191: 190 | B191: US-2023-114510 | C191: 44999 | D191: 45004 | E191: Standard Class | F191: JF-15295 | G191: Jason Fortune- | H191: Consumer | I191: United States | J191: Logan | K191: Utah | L191: 84321 | M191: West | N191: OFF-ST-10003221 | O191: Office Supplies | P191: Storage | Q191: Staple magnet | R191: 21.36 | S191: 2 | T191: 0 | U191: 5.7672
A192: 191 | B192: US-2023-114510 | C192: 44999 | D192: 45004 | E192: Standard Class | F192: JF-15295 | G192: Jason Fortune- | H192: Consumer | I192: United States | J192: Logan | K192: Utah | L192: 84321 | M192: West | N192: TEC-AC-10004877 | O192: Technology | P192: Accessories | Q192: Imation 30456 USB Flash Drive 8GB | R192: 82.8 | S192: 12 | T192: 0 | U192: 6.624
A193: 192 | B193: US-2023-152618 | C193: 44999 | D193: 45002 | E193: First Class | F193: RB-19465 | G193: Rick Bensley | H193: Home Office | I193: United States | J193: Chicago | K193: Illinois | L193: 60653 | M193: Central | N193: TEC-MA-10003626 | O193: Technology | P193: Machines | Q193: Hewlett-Packard Deskjet 6540 Color Inkjet Printer | R193: 574.91 | S193: 2 | T193: 0.3 | U193: 156.047
A194: 193 | B194: US-2023-149958 | C194: 45000 | D194: 45004 | E194: Standard Class | F194: AS-10240 | G194: Alan Shonely | H194: Consumer | I194: United States | J194: Tampa | K194: Florida | L194: 33614 | M194: South | N194: FUR-FU-10001756 | O194: Furniture | P194: Furnishings | Q194: Eldon Expressions Desk Accessory, Wood Photo Frame, Mahogany | R194: 45.696 | S194: 3 | T194: 0.2 | U194: 5.1408
... A450: 449 | B450: US-2023-166086 | C450: 45053 | D450: 45058 | E450: Standard Class | F450: CT-11995 | G450: Carol Triggs | H450: Consumer | I450: United States | J450: Lawrence | K450: Massachusetts | L450: 1841 | M450: East | N450: OFF-BI-10001078 | O450: Office Supplies | P450: Binders | Q450: Acco PRESSTEX Data Binder with Storage Hooks, Dark Blue, 14 7/8" X 11" | R450: 16.14 | S450: 3 | T450: 0 | U450: 7.9086
A451: 450 | B451: CA-2023-166086 | C451: 45053 | D451: 45058 | E451: Standard Class | F451: CT-11995 | G451: Carol Triggs | H451: Consumer | I451: Canada | J451: Toronto | K451: Ontario | L451: M3C | M451: East | N451: FUR-CH-10004675 | O451: Furniture | P451: Chairs | Q451: Lifetime Advantage Folding Chairs, 4/Carton | R451: 872.32 | S451: 4 | T451: 0 | U451: 244.2496
A452: 451 | B452: CA-2023-166086 | C452: 45053 | D452: 45058 | E452: Standard Class | F452: CT-11995 | G452: Carol Triggs | H452: Consumer | I452: Canada | J452: Toronto | K452: Ontario | L452: M3C | M452: East | N452: FUR-TA-10003469 | O452: Furniture | P452: Tables | Q452: Balt Split Level Computer Training Table | R452: 194.25 | S452: 2 | T452: 0.3 | U452: -38.85
A453: 452 | B453: CA-2023-166086 | C453: 45053 | D453: 45058 | E453: Standard Class | F453: CT-11995 | G453: Carol Triggs | H453: Consumer | I453: Canada | J453: Toronto | K453: Ontario | L453: M3C | M453: East | N453: OFF-AR-10002578 | O453: Office Supplies | P453: Art | Q453: Newell 335 | R453: 8.64 | S453: 3 | T453: 0 | U453: 2.5056
A454: 453 | B454: CA-2023-166086 | C454: 45053 | D454: 45058 | E454: Standard Class | F454: CT-11995 | G454: Carol Triggs | H454: Consumer | I454: Canada | J454: Toronto | K454: Ontario | L454: M3C | M454: East | N454: OFF-BI-10001078 | O454: Office Supplies | P454: Binders | Q454: Acco PRESSTEX Data Binder with Storage Hooks, Dark Blue, 14 7/8" X 11" | R454: 16.14 | S454: 3 | T454: 0 | U454: 7.9086
A455: 454 | B455: US-2023-116666 | C455: 45054 | D455: 45056 | E455: First Class | F455: KT-16480 | G455: Kean Thornton | H455: Consumer | I455: United States | J455: Philadelphia | K455: Pennsylvania | L455: 19134 | M455: East | N455: TEC-CO-10001449 | O455: Technology | P455: Copiers | Q455: Hewlett Packard LaserJet 3310 Copier | R455: 1799.97 | S455: 5 | T455: 0.4 | U455: 239.996
A456: 455 | B456: US-2023-158771 | C456: 45055 | D456: 45055 | E456: Same Day | F456: SB-20290 | G456: Sean Braxton | H456: Corporate | I456: United States | J456: Henderson | K456: Kentucky | L456: 42420 | M456: South | N456: OFF-LA-10001641 | O456: Office Supplies | P456: Labels | Q456: Avery 518 | R456: 9.45 | S456: 3 | T456: 0 | U456: 4.536
A457: 456 | B457: US-2023-158771 | C457: 45055 | D457: 45055 | E457: Same Day | F457: SB-20290 | G457: Sean Braxton | H457: Corporate | I457: United States | J457: Henderson | K457: Kentucky | L457: 42420 | M457: South | N457: OFF-LA-10003121 | O457: Office Supplies | P457: Labels | Q457: Avery 506 | R457: 20.65 | S457: 5 | T457: 0 | U457: 9.499
A458: 457 | B458: US-2023-158771 | C458: 45055 | D458: 45055 | E458: Same Day | F458: SB-20290 | G458: Sean Braxton | H458: Corporate | I458: United States | J458: Henderson | K458: Kentucky | L458: 42420 | M458: South | N458: OFF-PA-10002689 | O458: Office Supplies | P458: Paper | Q458: Weyerhaeuser First Choice Laser/Copy Paper (20Lb. and 88 Bright) | R458: 45.36 | S458: 7 | T458: 0 | U458: 21.7728
A459: 458 | B459: US-2023-158771 | C459: 45055 | D459: 45055 | E459: Same Day | F459: SB-20290 | G459: Sean Braxton | H459: Corporate | I459: United States | J459: Henderson | K459: Kentucky | L459: 42420 | M459: South | N459: OFF-ST-10000107 | O459: Office Supplies | P459: Storage | Q459: Fellowes Super Stor/Drawer | R459: 83.25 | S459: 3 | T459: 0 | U459: 14.985
A460: 459 | B460: US-2023-102071 | C460: 45055 | D460: 45061 | E460: Standard Class | F460: PG-18820 | G460: Patrick Gardner | H460: Consumer | I460: United States | J460: San Francisco | K460: California | L460: 94110 | M460: West | N460: TEC-AC-10000109 | O460: Technology | P460: Accessories | Q460: Sony Micro Vault Click 16 GB USB 2.0 Flash Drive | R460: 167.97 | S460: 3 | T460: 0 | U460: 40.3128
A461: 460 | B461: US-2023-102071 | C461: 45055 | D461: 45061 | E461: Standard Class | F461: PG-18820 | G461: Patrick Gardner | H461: Consumer | I461: United States | J461: San Francisco | K461: California | L461: 94110 | M461: West | N461: TEC-AC-10003441 | O461: Technology | P461: Accessories | Q461: Kingston Digital DataTraveler 32GB USB 2.0 | R461: 67.8 | S461: 4 | T461: 0 | U461: 4.068
A462: 461 | B462: US-2023-114181 | C462: 45056 | D462: 45060 | E462: Second Class | F462: AF-10885 | G462: Art Foster | H462: Consumer | I462: United States | J462: Philadelphia | K462: Pennsylvania | L462: 19134 | M462: East | N462: FUR-BO-10004467 | O462: Furniture | P462: Bookcases | Q462: Bestar Classic Bookcase | R462: 349.965 | S462: 7 | T462: 0.5 | U462: -216.9783
A463: 462 | B463: US-2023-103310 | C463: 45056 | D463: 45061 | E463: Standard Class | F463: GM-14680 | G463: Greg Matthias | H463: Consumer | I463: United States | J463: San Jose | K463: California | L463: 95123 | M463: West | N463: FUR-CH-10002320 | O463: Furniture | P463: Chairs | Q463: Hon Pagoda Stacking Chairs | R463: 256.784 | S463: 1 | T463: 0.2 | U463: 32.098
A464: 463 | B464: US-2023-114181 | C464: 45056 | D464: 45060 | E464: Second Class | F464: AF-10885 | G464: Art Foster | H464: Consumer | I464: United States | J464: Philadelphia | K464: Pennsylvania | L464: 19134 | M464: East | N464: OFF-AR-10000716 | O464: Office Supplies | P464: Art | Q464: DIXON Ticonderoga Erasable Checking Pencils | R464: 22.32 | S464: 5 | T464: 0.2 | U464: 5.301
A465: 464 | B465: US-2023-159709 | C465: 45056 | D465: 45061 | E465: Standard Class | F465: AI-10855 | G465: Arianne Irving | H465: Consumer | I465: United States | J465: Kent | K465: Washington | L465: 98031 | M465: West | N465: OFF-EN-10001434 | O465: Office Supplies | P465: Envelopes | Q465: Strathmore #10 Envelopes, Ultimate White | R465: 158.13 | S465: 3 | T465: 0 | U465: 77.4837
A466: 465 | B466: US-2023-103310 | C466: 45056 | D466: 45061 | E466: Standard Class | F466: GM-14680 | G466: Greg Matthias | H466: Consumer | I466: United States | J466: San Jose | K466: California | L466: 95123 | M466: West | N466: OFF-PA-10004353 | O466: Office Supplies | P466: Paper | Q466: Southworth 25% Cotton Premium Laser Paper and Envelopes | R466: 39.96 | S466: 2 | T466: 0 | U466: 19.1808
... A502: 501 | B502: US-2023-130673 | C502: 45066 | D502: 45068 | E502: Second Class | F502: MC-17590 | G502: Matt Collister | H502: Corporate | I502: United States | J502: San Marcos | K502: Texas | L502: 78666 | M502: Central | N502: TEC-AC-10004227 | O502: Technology | P502: Accessories | Q502: SanDisk Ultra 16 GB MicroSDHC Class 10 Memory Card | R502: 20.784 | S502: 2 | T502: 0.2 | U502: -3.6372
A503: 502 | B503: CA-2023-166695 | C503: 45066 | D503: 45070 | E503: Standard Class | F503: CC-12430 | G503: Chuck Clark | H503: Home Office | I503: Canada | J503: Vancouver | K503: British Columbia | L503: V6Z | M503: West | N503: FUR-CH-10000225 | O503: Furniture | P503: Chairs | Q503: Global Geo Office Task Chair, Gray | R503: 518.27 | S503: 8 | T503: 0.2 | U503: -97.18
A504: 503 | B504: CA-2023-166695 | C504: 45066 | D504: 45070 | E504: Standard Class | F504: CC-12430 | G504: Chuck Clark | H504: Home Office | I504: Canada | J504: Vancouver | K504: British Columbia | L504: V6Z | M504: West | N504: FUR-FU-10002191 | O504: Furniture | P504: Furnishings | Q504: G.E. Halogen Desk Lamp Bulbs | R504: 6.98 | S504: 1 | T504: 0 | U504: 3.35
A505: 504 | B505: CA-2023-166695 | C505: 45066 | D505: 45070 | E505: Standard Class | F505: CC-12430 | G505: Chuck Clark | H505: Home Office | I505: Canada | J505: Vancouver | K505: British Columbia | L505: V6Z | M505: West | N505: TEC-MA-10003176 | O505: Technology | P505: Machines | Q505: Okidata B400 Printer | R505: 343.2 | S505: 1 | T505: 0.2 | U505: 38.61
A506: 505 | B506: US-2023-127166 | C506: 45067 | D506: 45069 | E506: Second Class | F506: KH-16360 | G506: Katherine Hughes | H506: Consumer | I506: United States | J506: Houston | K506: Texas | L506: 77070 | M506: Central | N506: FUR-CH-10003396 | O506: Furniture | P506: Chairs | Q506: Global Deluxe Steno Chair | R506: 107.772 | S506: 2 | T506: 0.3 | U506: -29.2524
A507: 506 | B507: US-2023-152443 | C507: 45067 | D507: 45072 | E507: Standard Class | F507: FG-14260 | G507: Frank Gastineau | H507: Home Office | I507: United States | J507: Lawrence | K507: Massachusetts | L507: 1841 | M507: East | N507: OFF-AP-10001293 | O507: Office Supplies | P507: Appliances | Q507: Belkin 8 Outlet Surge Protector | R507: 245.88 | S507: 6 | T507: 0 | U507: 68.8464
A508: 507 | B508: US-2023-104780 | C508: 45067 | D508: 45071 | E508: Standard Class | F508: BT-11530 | G508: Bradley Talbott | H508: Home Office | I508: United States | J508: San Diego | K508: California | L508: 92037 | M508: West | N508: OFF-AR-10003514 | O508: Office Supplies | P508: Art | Q508: 4009 Highlighters by Sanford | R508: 31.84 | S508: 8 | T508: 0 | U508: 10.5072
A509: 508 | B509: US-2023-127166 | C509: 45067 | D509: 45069 | E509: Second Class | F509: KH-16360 | G509: Katherine Hughes | H509: Consumer | I509: United States | J509: Houston | K509: Texas | L509: 77070 | M509: Central | N509: OFF-BI-10000977 | O509: Office Supplies | P509: Binders | Q509: Ibico Plastic Spiral Binding Combs | R509: 18.24 | S509: 3 | T509: 0.8 | U509: -31.008
A510: 509 | B510: US-2023-152443 | C510: 45067 | D510: 45072 | E510: Standard Class | F510: FG-14260 | G510: Frank Gastineau | H510: Home Office | I510: United States | J510: Lawrence | K510: Massachusetts | L510: 1841 | M510: East | N510: OFF-BI-10001071 | O510: Office Supplies | P510: Binders | Q510: GBC ProClick Punch Binding System | R510: 447.86 | S510: 7 | T510: 0 | U510: 219.4514
A511: 510 | B511: US-2023-117639 | C511: 45067 | D511: 45071 | E511: Standard Class | F511: MW-18235 | G511: Mitch Willingham | H511: Corporate | I511: United States | J511: Virginia Beach | K511: Virginia | L511: 23464 | M511: South | N511: OFF-BI-10003925 | O511: Office Supplies | P511: Binders | Q511: Fellowes PB300 Plastic Comb Binding Machine | R511: 2715.93 | S511: 7 | T511: 0 | U511: 1276.4871
A512: 511 | B512: US-2023-127166 | C512: 45067 | D512: 45069 | E512: Second Class | F512: KH-16360 | G512: Katherine Hughes | H512: Consumer | I512: United States | J512: Houston | K512: Texas | L512: 77070 | M512: Central | N512: OFF-EN-10003134 | O512: Office Supplies | P512: Envelopes | Q512: Staple envelope | R512: 56.064 | S512: 6 | T512: 0.2 | U512: 21.024
A513: 512 | B513: US-2023-127166 | C513: 45067 | D513: 45069 | E513: Second Class | F513: KH-16360 | G513: Katherine Hughes | H513: Consumer | I513: United States | J513: Houston | K513: Texas | L513: 77070 | M513: Central | N513: OFF-PA-10001560 | O513: Office Supplies | P513: Paper | Q513: Adams Telephone Message Books, 5 1/4” x 11” | R513: 4.832 | S513: 1 | T513: 0.2 | U513: 1.6308
A514: 513 | B514: US-2023-152443 | C514: 45067 | D514: 45072 | E514: Standard Class | F514: FG-14260 | G514: Frank Gastineau | H514: Home Office | I514: United States | J514: Lawrence | K514: Massachusetts | L514: 1841 | M514: East | N514: OFF-PA-10003022 | O514: Office Supplies | P514: Paper | Q514: Xerox 1992 | R514: 17.94 | S514: 3 | T514: 0 | U514: 8.7906
A515: 514 | B515: US-2023-117639 | C515: 45067 | D515: 45071 | E515: Standard Class | F515: MW-18235 | G515: Mitch Willingham | H515: Corporate | I515: United States | J515: Virginia Beach | K515: Virginia | L515: 23464 | M515: South | N515: TEC-PH-10001530 | O515: Technology | P515: Phones | Q515: Plantronics Voyager Pro Legend | R515: 617.97 | S515: 3 | T515: 0 | U515: 173.0316
A516: 515 | B516: CA-2023-152443 | C516: 45067 | D516: 45072 | E516: Standard Class | F516: FG-14260 | G516: Frank Gastineau | H516: Home Office | I516: Canada | J516: Montreal | K516: Quebec | L516: H1A | M516: East | N516: OFF-AP-10001293 | O516: Office Supplies | P516: Appliances | Q516: Belkin 8 Outlet Surge Protector | R516: 245.88 | S516: 6 | T516: 0 | U516: 68.8464
A517: 516 | B517: CA-2023-152443 | C517: 45067 | D517: 45072 | E517: Standard Class | F517: FG-14260 | G517: Frank Gastineau | H517: Home Office | I517: Canada | J517: Montreal | K517: Quebec | L517: H1A | M517: East | N517: OFF-BI-10001071 | O517: Office Supplies | P517: Binders | Q517: GBC ProClick Punch Binding System | R517: 447.86 | S517: 7 | T517: 0 | U517: 219.4514
A518: 517 | B518: CA-2023-152443 | C518: 45067 | D518: 45072 | E518: Standard Class | F518: FG-14260 | G518: Frank Gastineau | H518: Home Office | I518: Canada | J518: Montreal | K518: Quebec | L518: H1A | M518: East | N518: OFF-PA-10003022 | O518: Office Supplies | P518: Paper | Q518: Xerox 1992 | R518: 17.94 | S518: 3 | T518: 0 | U518: 8.7906
A519: 518 | B519: US-2023-143840 | C519: 45068 | D519: 45075 | E519: Standard Class | F519: EH-14185 | G519: Evan Henry | H519: Consumer | I519: United States | J519: Decatur | K519: Alabama | L519: 35601 | M519: South | N519: TEC-PH-10002660 | O519: Technology | P519: Phones | Q519: Nortel Networks T7316 E Nt8 B27 | R519: 135.98 | S519: 2 | T519: 0 | U519: 33.995
A520: 519 | B520: US-2023-143840 | C520: 45068 | D520: 45075 | E520: Standard Class | F520: EH-14185 | G520: Evan Henry | H520: Consumer | I520: United States | J520: Decatur | K520: Alabama | L520: 35601 | M520: South | N520: TEC-PH-10003171 | O520: Technology | P520: Phones | Q520: Plantronics Encore H101 Dual Earpieces Headset | R520: 44.95 | S520: 1 | T520: 0 | U520: 12.586
A521: 520 | B521: US-2023-135881 | C521: 45069 | D521: 45073 | E521: Standard Class | F521: GT-14710 | G521: Greg Tran | H521: Consumer | I521: United States | J521: New York City | K521: New York | L521: 10035 | M521: East | N521: OFF-AP-10002118 | O521: Office Supplies | P521: Appliances | Q521: 1.7 Cubic Foot Compact "Cube" Office Refrigerators | R521: 208.16 | S521: 1 | T521: 0 | U521: 56.2032
A522: 521 | B522: US-2023-105767 | C522: 45069 | D522: 45073 | E522: Standard Class | F522: AR-10510 | G522: Andrew Roberts | H522: Consumer | I522: United States | J522: Philadelphia | K522: Pennsylvania | L522: 19134 | M522: East | N522: OFF-AR-10001246 | O522: Office Supplies | P522: Art | Q522: Newell 317 | R522: 21.168 | S522: 9 | T522: 0.2 | U522: 2.3814
A523: 522 | B523: US-2023-135881 | C523: 45069 | D523: 45073 | E523: Standard Class | F523: GT-14710 | G523: Greg Tran | H523: Consumer | I523: United States | J523: New York City | K523: New York | L523: 10035 | M523: East | N523: OFF-BI-10000829 | O523: Office Supplies | P523: Binders | Q523: Avery Non-Stick Binders | R523: 17.96 | S523: 5 | T523: 0.2 | U523: 5.837
A524: 523 | B524: US-2023-105767 | C524: 45069 | D524: 45073 | E524: Standard Class | F524: AR-10510 | G524: Andrew Roberts | H524: Consumer | I524: United States | J524: Philadelphia | K524: Pennsylvania | L524: 19134 | M524: East | N524: OFF-BI-10000848 | O524: Office Supplies | P524: Binders | Q524: Angle-D Ring Binders | R524: 3.282 | S524: 2 | T524: 0.7 | U524: -2.6256
A525: 524 | B525: US-2023-138513 | C525: 45069 | D525: 45073 | E525: Standard Class | F525: EH-13990 | G525: Erica Hackney | H525: Consumer | I525: United States | J525: Bellevue | K525: Washington | L525: 98006 | M525: West | N525: OFF-PA-10003177 | O525: Office Supplies | P525: Paper | Q525: Xerox 1999 | R525: 12.96 | S525: 2 | T525: 0 | U525: 6.2208
A526: 525 | B526: US-2023-135881 | C526: 45069 | D526: 45073 | E526: Standard Class | F526: GT-14710 | G526: Greg Tran | H526: Consumer | I526: United States | J526: New York City | K526: New York | L526: 10035 | M526: East | N526: OFF-SU-10003002 | O526: Office Supplies | P526: Supplies | Q526: Letter Slitter | R526: 5.04 | S526: 2 | T526: 0 | U526: 0.1512
A527: 526 | B527: US-2023-105767 | C527: 45069 | D527: 45073 | E527: Standard Class | F527: AR-10510 | G527: Andrew Roberts | H527: Consumer | I527: United States | J527: Philadelphia | K527: Pennsylvania | L527: 19134 | M527: East | N527: TEC-PH-10003092 | O527: Technology | P527: Phones | Q527: Motorola L804 | R527: 55.188 | S527: 2 | T527: 0.4 | U527: -10.1178
A528: 527 | B528: US-2023-143413 | C528: 45070 | D528: 45076 | E528: Standard Class | F528: RP-19390 | G528: Resi Pölking | H528: Consumer | I528: United States | J528: Baltimore | K528: Maryland | L528: 21215 | M528: East | N528: OFF-PA-10002319 | O528: Office Supplies | P528: Paper | Q528: Xerox 1944 | R528: 116.28 | S528: 3 | T528: 0 | U528: 56.9772
A529: 528 | B529: US-2023-130379 | C529: 45071 | D529: 45075 | E529: Standard Class | F529: JL-15235 | G529: Janet Lee | H529: Consumer | I529: United States | J529: Chicago | K529: Illinois | L529: 60623 | M529: Central | N529: FUR-FU-10002553 | O529: Furniture | P529: Furnishings | Q529: Electrix Incandescent Magnifying Lamp, Black | R529: 29.32 | S529: 2 | T529: 0.6 | U529: -24.189
A530: 529 | B530: US-2023-130379 | C530: 45071 | D530: 45075 | E530: Standard Class | F530: JL-15235 | G530: Janet Lee | H530: Consumer | I530: United States | J530: Chicago | K530: Illinois | L530: 60623 | M530: Central | N530: OFF-AP-10001394 | O530: Office Supplies | P530: Appliances | Q530: Harmony Air Purifier | R530: 75.6 | S530: 2 | T530: 0.8 | U530: -166.32
... A631: 630 | B631: US-2023-123855 | C631: 45095 | D631: 45100 | E631: Standard Class | F631: MC-18100 | G631: Mick Crebagga | H631: Consumer | I631: United States | J631: Los Angeles | K631: California | L631: 90036 | M631: West | N631: TEC-PH-10000215 | O631: Technology | P631: Phones | Q631: Plantronics Cordless Phone Headset with In-line Volume - M214C | R631: 139.8 | S631: 5 | T631: 0.2 | U631: 12.2325
A632: 631 | B632: CA-2023-184712 | C632: 45095 | D632: 45097 | E632: Second Class | F632: NC-19470 | G632: Neil Cohen | H632: Home Office | I632: Canada | J632: Halifax | K632: Nova Scotia | L632: B3H | M632: East | N632: OFF-PA-10000167 | O632: Office Supplies | P632: Paper | Q632: Xerox 1925 | R632: 74.352 | S632: 3 | T632: 0.2 | U632: 23.235
A633: 632 | B633: US-2023-166863 | C633: 45097 | D633: 45101 | E633: Standard Class | F633: SC-20020 | G633: Sam Craven | H633: Consumer | I633: United States | J633: Plano | K633: Texas | L633: 75023 | M633: Central | N633: FUR-BO-10001608 | O633: Furniture | P633: Bookcases | Q633: Hon Metal Bookcases, Black | R633: 193.0656 | S633: 4 | T633: 0.32 | U633: -19.8744
A634: 633 | B634: US-2023-112949 | C634: 45097 | D634: 45104 | E634: Standard Class | F634: Co-12640 | G634: Corey-Lock | H634: Consumer | I634: United States | J634: Lawton | K634: Oklahoma | L634: 73505 | M634: Central | N634: OFF-AP-10001005 | O634: Office Supplies | P634: Appliances | Q634: Honeywell Quietcare HEPA Air Cleaner | R634: 471.9 | S634: 6 | T634: 0 | U634: 155.727
A635: 634 | B635: US-2023-112949 | C635: 45097 | D635: 45104 | E635: Standard Class | F635: Co-12640 | G635: Corey-Lock | H635: Consumer | I635: United States | J635: Lawton | K635: Oklahoma | L635: 73505 | M635: Central | N635: OFF-AR-10003469 | O635: Office Supplies | P635: Art | Q635: Nontoxic Chalk | R635: 3.52 | S635: 2 | T635: 0 | U635: 1.6896
A636: 635 | B636: US-2023-166863 | C636: 45097 | D636: 45101 | E636: Standard Class | F636: SC-20020 | G636: Sam Craven | H636: Consumer | I636: United States | J636: Plano | K636: Texas | L636: 75023 | M636: Central | N636: OFF-BI-10000756 | O636: Office Supplies | P636: Binders | Q636: Storex DuraTech Recycled Plastic Frosted Binders | R636: 3.392 | S636: 4 | T636: 0.8 | U636: -5.088
A637: 636 | B637: US-2023-166863 | C637: 45097 | D637: 45101 | E637: Standard Class | F637: SC-20020 | G637: Sam Craven | H637: Consumer | I637: United States | J637: Plano | K637: Texas | L637: 75023 | M637: Central | N637: OFF-PA-10000587 | O637: Office Supplies | P637: Paper | Q637: Array Parchment Paper, Assorted Colors | R637: 11.648 | S637: 2 | T637: 0.2 | U637: 4.0768
A638: 637 | B638: US-2023-166863 | C638: 45097 | D638: 45101 | E638: Standard Class | F638: SC-20020 | G638: Sam Craven | H638: Consumer | I638: United States | J638: Plano | K638: Texas | L638: 75023 | M638: Central | N638: OFF-PA-10001166 | O638: Office Supplies | P638: Paper | Q638: Xerox 2 | R638: 15.552 | S638: 3 | T638: 0.2 | U638: 5.4432
...

Sheet People
A1: Regional Manager | B1: Region
A2: Sadie Pawthorne | B2: West
A3: Chuck Magee | B3: East
A4: Roxanne Rodriguez | B4: Central
A5: Fred Suzuki | B5: South

Sheet Returns
A1: Order ID | B1: Returned
A2: US-2023-100762 | B2: Yes
A3: US-2023-100867 | B3: Yes
A4: US-2023-102652 | B4: Yes
A5: US-2023-103373 | B5: Yes
A6: US-2023-103744 | B6: Yes
A7: US-2023-103940 | B7: Yes
A8: US-2023-104829 | B8: Yes
A9: US-2023-105270 | B9: Yes
A10: US-2023-108609 | B10: Yes
A11: US-2023-108861 | B11: Yes
A12: US-2023-109918 | B12: Yes
... A297: US-2026-155999 | B297: Yes

Sheet analysis
A1: total sales | B1: =SUM(Orders!R2:R5437) -> 1258041.8
A2: total profit | B2: =SUM(Orders!U2:U5437) -> 148068.38
A3: total quantity | B3: =SUM(Orders!S2:S5437) -> 20631

Sheet Category Analysis
A1: Category | B1: Sales
A2: Furniture | B2: =SUMIF(Orders!O2:O5437,A2,Orders!R2:R5437) -> 422007.97
A3: Office Supplies | B3: =SUMIF(Orders!O2:O5437,A3,Orders!R2:R5437) -> 376099.02
A4: Technology | B4: =SUMIF(Orders!O2:O5437,A4,Orders!R2:R5437) -> 459934.84
A6: Region | B6: Sales
A7: Central | B7: =SUMIF(Orders!M2:M5437,A7,Orders!R2:R5437) -> 265133.28
A8: East | B8: =SUMIF(Orders!M2:M5437,A8,Orders!R2:R5437) -> 384831.11
A9: South | B9: =SUMIF(Orders!M2:M5437,A9,Orders!R2:R5437) -> 226907.02
A10: West | B10: =SUMIF(Orders!M2:M5437,A10,Orders!R2:R5437) -> 381170.42
A12: Month | B12: Sales
A13: January | B13: {=SUMPRODUCT((MONTH(Orders!C$2:C$5437)=1)*Orders!R$2:R$5437)} -> 51810.302
A14: February | B14: {=SUMPRODUCT((MONTH(Orders!C$2:C$5437)=2)*Orders!R$2:R$5437)} -> 39450.118
A15: March | B15: {=SUMPRODUCT((MONTH(Orders!C$2:C$5437)=3)*Orders!R$2:R$5437)} -> 149943.61
A16: April | B16: {=SUMPRODUCT((MONTH(Orders!C$2:C$5437)=4)*Orders!R$2:R$5437)} -> 101319.71
A17: May | B17: {=SUMPRODUCT((MONTH(Orders!C$2:C$5437)=5)*Orders!R$2:R$5437)} -> 113609.55
A18: June | B18: {=SUMPRODUCT((MONTH(Orders!C$2:C$5437)=6)*Orders!R$2:R$5437)} -> 100403.92
A19: July | B19: {=SUMPRODUCT((MONTH(Orders!C$2:C$5437)=7)*Orders!R$2:R$5437)} -> 103012.22
A20: August | B20: {=SUMPRODUCT((MONTH(Orders!C$2:C$5437)=8)*Orders!R$2:R$5437)} -> 85034.079
A21: September | B21: {=SUMPRODUCT((MONTH(Orders!C$2:C$5437)=9)*Orders!R$2:R$5437)} -> 147297.47
A22: October | B22: {=SUMPRODUCT((MONTH(Orders!C$2:C$5437)=10)*Orders!R$2:R$5437)} -> 63820.472
A23: November | B23: {=SUMPRODUCT((MONTH(Orders!C$2:C$5437)=11)*Orders!R$2:R$5437)} -> 154799.52
A24: December | B24: {=SUMPRODUCT((MONTH(Orders!C$2:C$5437)=12)*Orders!R$2:R$5437)} -> 147540.87
A27: product name | B27: Sales
A28: {=_xlfn.SORTBY(_xlfn.UNIQUE(Orders!Q2:Q5437),SUMIF(Orders!Q2:Q5437,_xlfn.UNIQUE(Orders!Q2:Q5437),Orders!R2:R5437),-1)} -> Cisco TelePresence System EX90 Videoconferencing Unit | B28: =SUMIF(Orders!Q$2:Q$5437,A28,Orders!R$2:R$5437) -> 22638.48
A29: Fellowes PB500 Electric Punch Plastic Comb Binding Machine with Manual Bind | B29: =SUMIF(Orders!Q$2:Q$5437,A29,Orders!R$2:R$5437) -> 19064.85
A30: HP Designjet T520 Inkjet Large Format Printer - 24" Color | B30: =SUMIF(Orders!Q$2:Q$5437,A30,Orders!R$2:R$5437) -> 18374.895
A31: High Speed Automatic Electric Letter Opener | B31: =SUMIF(Orders!Q$2:Q$5437,A31,Orders!R$2:R$5437) -> 17030.312
A32: HON 5400 Series Task Chairs for Big and Tall | B32: =SUMIF(Orders!Q$2:Q$5437,A32,Orders!R$2:R$5437) -> 14650.482
A33: Riverside Palais Royal Lawyers Bookcase, Royale Cherry Finish | B33: =SUMIF(Orders!Q$2:Q$5437,A33,Orders!R$2:R$5437) -> 11717.034
A34: Lexmark MX611dhe Monochrome Laser Printer | B34: =SUMIF(Orders!Q$2:Q$5437,A34,Orders!R$2:R$5437) -> 11219.934
A35: Apple iPhone 5 | B35: =SUMIF(Orders!Q$2:Q$5437,A35,Orders!R$2:R$5437) -> 10527.246
A36: Tennsco 6- and 18-Compartment Lockers | B36: =SUMIF(Orders!Q$2:Q$5437,A36,Orders!R$2:R$5437) -> 9546.12
A37: Ibico EPK-21 Electric Binding System | B37: =SUMIF(Orders!Q$2:Q$5437,A37,Orders!R$2:R$5437) -> 9449.95
A38: SAFCO Arco Folding Chair
A39: Global Deluxe High-Back Manager's Chair
A40: 3D Systems Cube Printer, 2nd Generation, Magenta
A41: Canon PC1060 Personal Laser Copier
A42: Canon imageCLASS 2200 Advanced Copier
A43: Okidata MB760 Printer
A44: Ativa V4110MDD Micro-Cut Shredder
A45: Bretford Rectangular Conference Table Tops
A46: DMI Eclipse Executive Suite Bookcases
A47: GBC DocuBind TL300 Electric Binding System
A48: Zebra ZM400 Thermal Label Printer
A49: GBC Ibimaster 500 Manual ProClick Binding System
... A1766: Wilson Jones DublLock D-Ring Binders
